declback/__init__.py
declback-1.1.0.dist-info/LICENSE
declback-1.1.0.dist-info/METADATA
declback-1.1.0.dist-info/WHEEL
declback-1.1.0.dist-info/top_level.txt
declback-1.1.0.dist-info/RECORD
