Metadata-Version: 2.1
Name: declback
Version: 1.1.0
Summary: Declarative backend framework
Author-email: Kamaletdinov Karim <450906k@gmail.com>
License: Copyright (c) 2023 Karim Kamaletdinov
Project-URL: Homepage, https://github.com/declback/declback-py
Keywords: feed,reader,tutorial
Classifier: License :: OSI Approved :: MIT License
Classifier: Programming Language :: Python
Classifier: Programming Language :: Python :: 3
Requires-Python: >=3.10
License-File: LICENSE
Provides-Extra: dev
Requires-Dist: pytest ; extra == 'dev'
Requires-Dist: twine ; extra == 'dev'
Requires-Dist: build ; extra == 'dev'
